searchstring/__init__.py
searchstring-0.1.0.dist-info/METADATA
searchstring-0.1.0.dist-info/WHEEL
searchstring-0.1.0.dist-info/top_level.txt
searchstring-0.1.0.dist-info/RECORD
